MANIFEST.in
README.rst
setup.py
django_url_methods.egg-info/PKG-INFO
django_url_methods.egg-info/SOURCES.txt
django_url_methods.egg-info/dependency_links.txt
django_url_methods.egg-info/not-zip-safe
django_url_methods.egg-info/top_level.txt
urlmethods/__init__.py
urlmethods/__init__.pyc
urlmethods/models.py
urlmethods/models.pyc
urlmethods/tests.py
urlmethods/tests.pyc
urlmethods/threadmethod.py
urlmethods/threadmethod.pyc
urlmethods/urlmethods.py
urlmethods/urlmethods.pyc